starmf_proxy/__init__.py
starmf_proxy/enums.py
starmf_proxy/models.py
starmf_proxy/proxy.py
starmf_proxy/settings.py
starmf_proxy/starmf.py
starmf_proxy-0.0.2.dist-info/LICENCE
starmf_proxy-0.0.2.dist-info/METADATA
starmf_proxy-0.0.2.dist-info/WHEEL
starmf_proxy-0.0.2.dist-info/top_level.txt
starmf_proxy-0.0.2.dist-info/RECORD
